hoper/__init__.py
hoper/__main__.py
hoper/_args.py
hoper/_print.py
hoper/hoper.py
hoper/meta.py
hoper/util/__init__.py
hoper/util/header_redirect_util.py
hoper/util/history_util.py
hoper/util/hooks.py
hoper/util/js_redirect_util.py
hoper/util/proxy_parser.py
hoper/util/store.py
hoper/util/types.py
hoper/util/utils.py
hoper-2.7.1.dist-info/LICENSE
hoper-2.7.1.dist-info/METADATA
hoper-2.7.1.dist-info/WHEEL
hoper-2.7.1.dist-info/entry_points.txt
hoper-2.7.1.dist-info/top_level.txt
hoper-2.7.1.dist-info/RECORD
