Metadata-Version: 2.1
Name: hoper
Version: 2.7.1
Summary: Url redirects history assistant
Home-page: https://github.com/1271/hoper
Author: Sergey Zharkov
Author-email: sttv-pc@mail.ru
License: MIT
Download-URL: https://github.com/1271/hoper/archive/2.7.1.tar.gz
Keywords: hoper,redirects,url analyze
Platform: UNKNOWN
Classifier: Development Status :: 5 - Production/Stable
Classifier: License :: OSI Approved :: MIT License
Classifier: Natural Language :: English
Classifier: Environment :: Console
Classifier: Programming Language :: Python :: 3.6
Classifier: Programming Language :: Python :: 3.7
Classifier: Programming Language :: Python :: 3.8
Classifier: Programming Language :: Python :: 3.9
Classifier: Topic :: Internet :: WWW/HTTP
Requires-Python: >=3.6
Requires-Dist: requests
